flask_graphite/__init__.py
flask_graphite/hooks.py
flask_graphite/request_hooks.py
flask_graphite/utils.py
Flask_Graphite-0.6.0.dist-info/LICENSE
Flask_Graphite-0.6.0.dist-info/METADATA
Flask_Graphite-0.6.0.dist-info/WHEEL
Flask_Graphite-0.6.0.dist-info/top_level.txt
Flask_Graphite-0.6.0.dist-info/RECORD
