Metadata-Version: 2.1
Name: Flask-Graphite
Version: 0.6.0
Summary: Push useful metrics for each request without effort!
Home-page: https://github.com/numberly/flask-graphite
Author: numberly
Author-email: ramnes@1000mercis.com
License: MIT
Platform: UNKNOWN
Classifier: Environment :: Web Environment
Classifier: Intended Audience :: Developers
Classifier: Operating System :: OS Independent
Classifier: Programming Language :: Python
Classifier: Topic :: Internet :: WWW/HTTP :: Dynamic Content
Classifier: Topic :: Software Development :: Libraries :: Python Modules
Requires-Dist: Flask (>=0.12)
Requires-Dist: graphitesend (>=0.10.0)
